vancouver_food/__init__.py
vancouver_food/vancouver_dishes.py
vancouver_food-0.0.5.dist-info/METADATA
vancouver_food-0.0.5.dist-info/WHEEL
vancouver_food-0.0.5.dist-info/top_level.txt
vancouver_food-0.0.5.dist-info/RECORD
