Metadata-Version: 2.1
Name: vancouver-food
Version: 0.0.5
Summary: Let us help you pick a dish in Vancouver.
Home-page: UNKNOWN
Author: LeviLiao
Author-email: <dlnx38@gmail.com>
License: UNKNOWN
Keywords: vancouver,dishes
Platform: UNKNOWN
Classifier: Intended Audience :: Developers
Classifier: Programming Language :: Python :: 3
Classifier: Operating System :: OS Independent
